justshowit/__init__.py
justshowit/checker.py
justshowit/collage.py
justshowit/config.py
justshowit/encoded_font_data.py
justshowit/grid.py
justshowit/image_modifier.py
justshowit/parsers.py
justshowit/show.py
justshowit/utils.py
justshowit/video.py
justshowit/video_player.py
justshowit-0.3.6.dist-info/METADATA
justshowit-0.3.6.dist-info/WHEEL
justshowit-0.3.6.dist-info/top_level.txt
justshowit-0.3.6.dist-info/RECORD
