Metadata-Version: 2.1
Name: justshowit
Version: 0.3.6
Summary: Display images without all the nonsense!
Home-page: https://github.com/Jako-K/justshowit
Author: Jako-K
Requires-Dist: opencv-python
Requires-Dist: requests
Requires-Dist: numpy
Requires-Dist: Pillow
Requires-Dist: tqdm
